osc_lib/__init__.py
osc_lib/clientmanager.py
osc_lib/exceptions.py
osc_lib/i18n.py
osc_lib/logs.py
osc_lib/py.typed
osc_lib/shell.py
osc_lib/version.py
osc_lib/api/__init__.py
osc_lib/api/api.py
osc_lib/api/auth.py
osc_lib/api/utils.py
osc_lib/cli/__init__.py
osc_lib/cli/client_config.py
osc_lib/cli/format_columns.py
osc_lib/cli/identity.py
osc_lib/cli/pagination.py
osc_lib/cli/parseractions.py
osc_lib/command/__init__.py
osc_lib/command/command.py
osc_lib/command/commandmanager.py
osc_lib/command/timing.py
osc_lib/test/__init__.py
osc_lib/test/base.py
osc_lib/test/fakes.py
osc_lib/test/utils.py
osc_lib/tests/__init__.py
osc_lib/tests/fakes.py
osc_lib/tests/test_clientmanager.py
osc_lib/tests/test_logs.py
osc_lib/tests/test_shell.py
osc_lib/tests/api/__init__.py
osc_lib/tests/api/fakes.py
osc_lib/tests/api/test_api.py
osc_lib/tests/api/test_utils.py
osc_lib/tests/cli/__init__.py
osc_lib/tests/cli/test_client_config.py
osc_lib/tests/cli/test_format_columns.py
osc_lib/tests/cli/test_identity.py
osc_lib/tests/cli/test_parseractions.py
osc_lib/tests/command/__init__.py
osc_lib/tests/command/test_command.py
osc_lib/tests/command/test_timing.py
osc_lib/tests/utils/__init__.py
osc_lib/tests/utils/test_columns.py
osc_lib/tests/utils/test_tags.py
osc_lib/tests/utils/test_utils.py
osc_lib/utils/__init__.py
osc_lib/utils/columns.py
osc_lib/utils/tags.py
osc_lib-4.3.0.dist-info/licenses/AUTHORS
osc_lib-4.3.0.dist-info/licenses/LICENSE
osc_lib-4.3.0.dist-info/METADATA
osc_lib-4.3.0.dist-info/WHEEL
osc_lib-4.3.0.dist-info/pbr.json
osc_lib-4.3.0.dist-info/top_level.txt
osc_lib-4.3.0.dist-info/RECORD
