Metadata-Version: 2.4
Name: osc-lib
Version: 4.3.0
Summary: OpenStackClient Library
Author-email: OpenStack <openstack-discuss@lists.openstack.org>
License: Apache-2.0
Project-URL: Homepage, https://docs.openstack.org/osc-lib/
Project-URL: Repository, https://opendev.org/openstack/osc-lib/
Project-URL: Bug Tracker, https://storyboard.openstack.org/#!/project/openstack/osc-lib
Classifier: Development Status :: 5 - Production/Stable
Classifier: Environment :: OpenStack
Classifier: Intended Audience :: Developers
Classifier: License :: OSI Approved :: Apache Software License
Classifier: Operating System :: POSIX :: Linux
Classifier: Programming Language :: Python
Classifier: Programming Language :: Python :: 3
Classifier: Programming Language :: Python :: 3.10
Classifier: Programming Language :: Python :: 3.11
Classifier: Programming Language :: Python :: 3.12
Classifier: Programming Language :: Python :: 3.13
Requires-Python: >=3.10
License-File: LICENSE
Requires-Dist: cliff>=4.9.0
Requires-Dist: keystoneauth1>=5.10.0
Requires-Dist: openstacksdk>=0.15.0
Requires-Dist: oslo.i18n>=3.15.3
Requires-Dist: oslo.utils>=3.33.0
Requires-Dist: pbr!=2.1.0,>=2.0.0
Requires-Dist: requests>=2.14.2
Requires-Dist: stevedore>=1.20.0
Provides-Extra: test
Requires-Dist: fixtures>=3.0.0; extra == "test"
Requires-Dist: testtools>=2.2.0; extra == "test"
Dynamic: license-file
Dynamic: requires-dist
